LICENSE
MANIFEST.in
README.rst
setup.py
cronfield/__init__.py
cronfield/forms.py
cronfield/models.py
cronfield/static/cronfield/crontab_widget.css
cronfield/static/cronfield/crontab_widget.js
django_cronfield.egg-info/PKG-INFO
django_cronfield.egg-info/SOURCES.txt
django_cronfield.egg-info/dependency_links.txt
django_cronfield.egg-info/top_level.txt