Metadata-Version: 1.1
Name: django-cronfield
Version: 0.2
Summary: Simple CRON field with nice javascript-enabled User Interface and Cron format validation.
Home-page: https://github.com/knaperek/django-cronfield
Author: Jozef Knaperek & Emilia Knaperekova
Author-email: jknaperek@gmail.com
License: BSD License
Platform: UNKNOWN
Classifier: Environment :: Web Environment
Classifier: Framework :: Django
Classifier: Intended Audience :: Developers
Classifier: License :: OSI Approved :: BSD License
Classifier: Operating System :: OS Independent
Classifier: Programming Language :: Python
Classifier: Programming Language :: Python :: 2.7
Classifier: Topic :: Internet :: WWW/HTTP
Classifier: Topic :: Internet :: WWW/HTTP :: Dynamic Content
